{
      "website_domain": "t.me",
      "tranco_rank": 93,
      "crawl_mode": "Desktop",
      "pageload_start_ts": "05/06/2022 10:57:53.662212",
      "pageload_end_ts": "05/06/2022 10:57:56.205247",
      "post_pageload_url": "https://telegram.org/",
      "consent_status": "not_found",
      "cookies": [
            {
                  "stel_ssid": "6cc4d8084b70342ea6_9512895035509195428",
                  "expires": "Mon, 06 Jun 2022 08:57:54 GMT",
                  "path": "/",
                  "samesite": "None",
                  "secure": true,
                  "HttpOnly": true,
                  "size": 38
            },
            {
                  "stel_ssid": "166804baf978665462_18416765889666725392",
                  "expires": "Sun, 05 Jun 2022 20:04:34 GMT",
                  "path": "/",
                  "samesite": "None",
                  "secure": true,
                  "HttpOnly": true,
                  "size": 39
            }
      ],
      "third_party_domains": [
            "telegram.org"
      ],
      "redirect_pairs": [
            [
                  "t.me",
                  "telegram.org"
            ],
            [
                  "t.me",
                  "telegram.org"
            ]
      ],
      "requests_list": [
            {
                  "request_url": "https://t.me/",
                  "timestamp": "05/06/2022 10:57:53.924913",
                  "request_headers": {
                        "upgrade-insecure-requests": "1",
                        "user-agent": "Mozilla/5.0 (Windows NT 10.0; Win64; x64) AppleWebKit/537.36 (KHTML, like Gecko) HeadlessChrome/102.0.5005.63 Safari/537.36",
                        "accept": "text/html,application/xhtml+xml,application/xml;q=0.9,image/avif,image/webp,image/apng,*/*;q=0.8,application/signed-exchange;v=b3;q=0.9",
                        "sec-fetch-site": "none",
                        "sec-fetch-mode": "navigate",
                        "sec-fetch-user": "?1",
                        "sec-fetch-dest": "document",
                        "accept-encoding": "gzip, deflate, br",
                        "accept-language": "en-GB"
                  },
                  "response_headers": {
                        "server": "nginx/1.18.0",
                        "date": "Sun, 05 Jun 2022 08:57:54 GMT",
                        "content-type": "text/html; charset=UTF-8",
                        "content-length": "20",
                        "set-cookie": "stel_ssid=6cc4d8084b70342ea6_9512895035509195428; expires=Mon, 06 Jun 2022 08:57:54 GMT; path=/; samesite=None; secure; HttpOnly",
                        "pragma": "no-cache",
                        "cache-control": "no-store",
                        "location": "//telegram.org/",
                        "content-encoding": "gzip",
                        "strict-transport-security": "max-age=35768000"
                  },
                  "nr_cookies": 0
            },
            {
                  "request_url": "https://telegram.org/",
                  "timestamp": "05/06/2022 10:57:54.249233",
                  "request_headers": {
                        "upgrade-insecure-requests": "1",
                        "user-agent": "Mozilla/5.0 (Windows NT 10.0; Win64; x64) AppleWebKit/537.36 (KHTML, like Gecko) HeadlessChrome/102.0.5005.63 Safari/537.36",
                        "accept": "text/html,application/xhtml+xml,application/xml;q=0.9,image/avif,image/webp,image/apng,*/*;q=0.8,application/signed-exchange;v=b3;q=0.9",
                        "sec-fetch-site": "none",
                        "sec-fetch-mode": "navigate",
                        "sec-fetch-user": "?1",
                        "sec-fetch-dest": "document",
                        "accept-encoding": "gzip, deflate, br",
                        "accept-language": "en-GB"
                  },
                  "response_headers": {
                        "server": "nginx/1.18.0",
                        "date": "Sun, 05 Jun 2022 08:57:54 GMT",
                        "content-type": "text/html; charset=utf-8",
                        "content-length": "5944",
                        "set-cookie": "stel_ssid=166804baf978665462_18416765889666725392; expires=Sun, 05 Jun 2022 20:04:34 GMT; path=/; samesite=None; secure; HttpOnly",
                        "pragma": "no-cache",
                        "cache-control": "no-store",
                        "x-frame-options": "SAMEORIGIN",
                        "content-encoding": "gzip",
                        "strict-transport-security": "max-age=31536000; includeSubDomains; preload"
                  },
                  "nr_cookies": 0
            },
            {
                  "request_url": "https://telegram.org/css/telegram.css?230",
                  "timestamp": "05/06/2022 10:57:54.544795",
                  "request_headers": {
                        "sec-ch-ua": "",
                        "sec-ch-ua-mobile": "?0",
                        "user-agent": "Mozilla/5.0 (Windows NT 10.0; Win64; x64) AppleWebKit/537.36 (KHTML, like Gecko) HeadlessChrome/102.0.5005.63 Safari/537.36",
                        "sec-ch-ua-platform": "",
                        "accept": "text/css,*/*;q=0.1",
                        "sec-fetch-site": "same-origin",
                        "sec-fetch-mode": "no-cors",
                        "sec-fetch-dest": "style",
                        "referer": "https://telegram.org/",
                        "accept-encoding": "gzip, deflate, br",
                        "accept-language": "en-GB",
                        "cookie": "stel_ssid=166804baf978665462_18416765889666725392"
                  },
                  "response_headers": {
                        "server": "nginx/1.18.0",
                        "date": "Sun, 05 Jun 2022 08:57:55 GMT",
                        "content-type": "text/css",
                        "last-modified": "Fri, 06 May 2022 15:46:52 GMT",
                        "etag": "W/\"627542ec-1ca4e\"",
                        "expires": "Thu, 09 Jun 2022 08:57:55 GMT",
                        "cache-control": "max-age=345600",
                        "strict-transport-security": "max-age=31536000; includeSubDomains; preload",
                        "content-encoding": "gzip"
                  },
                  "nr_cookies": 1
            },
            {
                  "request_url": "https://telegram.org/js/main.js?46",
                  "timestamp": "05/06/2022 10:57:54.548795",
                  "request_headers": {
                        "sec-ch-ua": "",
                        "sec-ch-ua-mobile": "?0",
                        "user-agent": "Mozilla/5.0 (Windows NT 10.0; Win64; x64) AppleWebKit/537.36 (KHTML, like Gecko) HeadlessChrome/102.0.5005.63 Safari/537.36",
                        "sec-ch-ua-platform": "",
                        "accept": "*/*",
                        "sec-fetch-site": "same-origin",
                        "sec-fetch-mode": "no-cors",
                        "sec-fetch-dest": "script",
                        "referer": "https://telegram.org/",
                        "accept-encoding": "gzip, deflate, br",
                        "accept-language": "en-GB",
                        "cookie": "stel_ssid=166804baf978665462_18416765889666725392"
                  },
                  "response_headers": {
                        "server": "nginx/1.18.0",
                        "date": "Sun, 05 Jun 2022 08:57:55 GMT",
                        "content-type": "application/javascript",
                        "last-modified": "Tue, 19 Apr 2022 11:15:29 GMT",
                        "etag": "W/\"625e99d1-539b\"",
                        "expires": "Thu, 09 Jun 2022 08:57:55 GMT",
                        "cache-control": "max-age=345600",
                        "strict-transport-security": "max-age=31536000; includeSubDomains; preload",
                        "content-encoding": "gzip"
                  },
                  "nr_cookies": 1
            },
            {
                  "request_url": "https://telegram.org/css/bootstrap.min.css?3",
                  "timestamp": "05/06/2022 10:57:54.550796",
                  "request_headers": {
                        "sec-ch-ua": "",
                        "sec-ch-ua-mobile": "?0",
                        "user-agent": "Mozilla/5.0 (Windows NT 10.0; Win64; x64) AppleWebKit/537.36 (KHTML, like Gecko) HeadlessChrome/102.0.5005.63 Safari/537.36",
                        "sec-ch-ua-platform": "",
                        "accept": "text/css,*/*;q=0.1",
                        "sec-fetch-site": "same-origin",
                        "sec-fetch-mode": "no-cors",
                        "sec-fetch-dest": "style",
                        "referer": "https://telegram.org/",
                        "accept-encoding": "gzip, deflate, br",
                        "accept-language": "en-GB",
                        "cookie": "stel_ssid=166804baf978665462_18416765889666725392"
                  },
                  "response_headers": {
                        "server": "nginx/1.18.0",
                        "date": "Sun, 05 Jun 2022 08:57:55 GMT",
                        "content-type": "text/css",
                        "last-modified": "Fri, 10 Nov 2017 17:54:14 GMT",
                        "etag": "W/\"5a05e7c6-a61b\"",
                        "expires": "Thu, 09 Jun 2022 08:57:55 GMT",
                        "cache-control": "max-age=345600",
                        "strict-transport-security": "max-age=31536000; includeSubDomains; preload",
                        "content-encoding": "gzip"
                  },
                  "nr_cookies": 1
            },
            {
                  "request_url": "https://telegram.org/file/464001531/fb90/y871yZUW70Y.372928/9fdf3a084a04b47ec8",
                  "timestamp": "05/06/2022 10:57:54.560196",
                  "request_headers": {
                        "sec-ch-ua": "",
                        "sec-ch-ua-mobile": "?0",
                        "user-agent": "Mozilla/5.0 (Windows NT 10.0; Win64; x64) AppleWebKit/537.36 (KHTML, like Gecko) HeadlessChrome/102.0.5005.63 Safari/537.36",
                        "sec-ch-ua-platform": "",
                        "accept": "image/avif,image/webp,image/apng,image/svg+xml,image/*,*/*;q=0.8",
                        "sec-fetch-site": "same-origin",
                        "sec-fetch-mode": "no-cors",
                        "sec-fetch-dest": "image",
                        "referer": "https://telegram.org/",
                        "accept-encoding": "gzip, deflate, br",
                        "accept-language": "en-GB",
                        "cookie": "stel_ssid=166804baf978665462_18416765889666725392"
                  },
                  "response_headers": {
                        "server": "nginx/1.18.0",
                        "date": "Sun, 05 Jun 2022 08:57:55 GMT",
                        "content-type": "image/jpeg",
                        "content-length": "297775",
                        "cache-control": "max-age=2592000, public",
                        "expires": "Tue, 05 Jul 2022 08:57:55 GMT",
                        "etag": "\"75dc53b997536b03aa196c25886d32db74ef4c6c\"",
                        "content-encoding": "gzip",
                        "strict-transport-security": "max-age=31536000; includeSubDomains; preload"
                  },
                  "nr_cookies": 1
            },
            {
                  "request_url": "https://telegram.org/js/tgsticker.js?27",
                  "timestamp": "05/06/2022 10:57:54.562196",
                  "request_headers": {
                        "sec-ch-ua": "",
                        "sec-ch-ua-mobile": "?0",
                        "user-agent": "Mozilla/5.0 (Windows NT 10.0; Win64; x64) AppleWebKit/537.36 (KHTML, like Gecko) HeadlessChrome/102.0.5005.63 Safari/537.36",
                        "sec-ch-ua-platform": "",
                        "accept": "*/*",
                        "sec-fetch-site": "same-origin",
                        "sec-fetch-mode": "no-cors",
                        "sec-fetch-dest": "script",
                        "referer": "https://telegram.org/",
                        "accept-encoding": "gzip, deflate, br",
                        "accept-language": "en-GB",
                        "cookie": "stel_ssid=166804baf978665462_18416765889666725392"
                  },
                  "response_headers": {
                        "server": "nginx/1.18.0",
                        "date": "Sun, 05 Jun 2022 08:57:55 GMT",
                        "content-type": "application/javascript",
                        "last-modified": "Sat, 09 Apr 2022 12:24:06 GMT",
                        "etag": "W/\"62517ae6-38ec\"",
                        "expires": "Thu, 09 Jun 2022 08:57:55 GMT",
                        "cache-control": "max-age=345600",
                        "strict-transport-security": "max-age=31536000; includeSubDomains; preload",
                        "content-encoding": "gzip"
                  },
                  "nr_cookies": 1
            },
            {
                  "request_url": "https://telegram.org/file/464001418/12513/cF-RXvZE-6U.103646/9abb402fe4e74b126f",
                  "timestamp": "05/06/2022 10:57:54.565197",
                  "request_headers": {
                        "sec-ch-ua": "",
                        "sec-ch-ua-mobile": "?0",
                        "user-agent": "Mozilla/5.0 (Windows NT 10.0; Win64; x64) AppleWebKit/537.36 (KHTML, like Gecko) HeadlessChrome/102.0.5005.63 Safari/537.36",
                        "sec-ch-ua-platform": "",
                        "accept": "image/avif,image/webp,image/apng,image/svg+xml,image/*,*/*;q=0.8",
                        "sec-fetch-site": "same-origin",
                        "sec-fetch-mode": "no-cors",
                        "sec-fetch-dest": "image",
                        "referer": "https://telegram.org/",
                        "accept-encoding": "gzip, deflate, br",
                        "accept-language": "en-GB",
                        "cookie": "stel_ssid=166804baf978665462_18416765889666725392"
                  },
                  "response_headers": {
                        "server": "nginx/1.18.0",
                        "date": "Sun, 05 Jun 2022 08:57:55 GMT",
                        "content-type": "image/jpeg",
                        "content-length": "102971",
                        "cache-control": "max-age=2592000, public",
                        "expires": "Tue, 05 Jul 2022 08:57:55 GMT",
                        "etag": "\"f447d82f7ee357f669eb9d2ea93feef70fa558ef\"",
                        "content-encoding": "gzip",
                        "strict-transport-security": "max-age=31536000; includeSubDomains; preload"
                  },
                  "nr_cookies": 1
            },
            {
                  "request_url": "https://telegram.org/file/464001897/3/f0Go0rLpEwk.11343.png/dd4eeb46cc5efc0688",
                  "timestamp": "05/06/2022 10:57:54.567197",
                  "request_headers": {
                        "sec-ch-ua": "",
                        "sec-ch-ua-mobile": "?0",
                        "user-agent": "Mozilla/5.0 (Windows NT 10.0; Win64; x64) AppleWebKit/537.36 (KHTML, like Gecko) HeadlessChrome/102.0.5005.63 Safari/537.36",
                        "sec-ch-ua-platform": "",
                        "accept": "image/avif,image/webp,image/apng,image/svg+xml,image/*,*/*;q=0.8",
                        "sec-fetch-site": "same-origin",
                        "sec-fetch-mode": "no-cors",
                        "sec-fetch-dest": "image",
                        "referer": "https://telegram.org/",
                        "accept-encoding": "gzip, deflate, br",
                        "accept-language": "en-GB",
                        "cookie": "stel_ssid=166804baf978665462_18416765889666725392"
                  },
                  "response_headers": {
                        "server": "nginx/1.18.0",
                        "date": "Sun, 05 Jun 2022 08:57:55 GMT",
                        "content-type": "image/png",
                        "content-length": "11348",
                        "cache-control": "max-age=2592000, public",
                        "expires": "Tue, 05 Jul 2022 08:57:55 GMT",
                        "etag": "\"183936b397813281d8de1b217deb5c565bde1c5b\"",
                        "content-encoding": "gzip",
                        "strict-transport-security": "max-age=31536000; includeSubDomains; preload"
                  },
                  "nr_cookies": 1
            },
            {
                  "request_url": "https://telegram.org/file/464001166/2/FzTl8_M5mQA.19325.png/b6c5dbc0e4f6553805",
                  "timestamp": "05/06/2022 10:57:54.576465",
                  "request_headers": {
                        "sec-ch-ua": "",
                        "sec-ch-ua-mobile": "?0",
                        "user-agent": "Mozilla/5.0 (Windows NT 10.0; Win64; x64) AppleWebKit/537.36 (KHTML, like Gecko) HeadlessChrome/102.0.5005.63 Safari/537.36",
                        "sec-ch-ua-platform": "",
                        "accept": "image/avif,image/webp,image/apng,image/svg+xml,image/*,*/*;q=0.8",
                        "sec-fetch-site": "same-origin",
                        "sec-fetch-mode": "no-cors",
                        "sec-fetch-dest": "image",
                        "referer": "https://telegram.org/",
                        "accept-encoding": "gzip, deflate, br",
                        "accept-language": "en-GB",
                        "cookie": "stel_ssid=166804baf978665462_18416765889666725392"
                  },
                  "response_headers": {
                        "server": "nginx/1.18.0",
                        "date": "Sun, 05 Jun 2022 08:57:55 GMT",
                        "content-type": "image/png",
                        "content-length": "19348",
                        "cache-control": "max-age=2592000, public",
                        "expires": "Tue, 05 Jul 2022 08:57:55 GMT",
                        "etag": "\"2690d1e344526d5a2fb08060299f2697537643ae\"",
                        "content-encoding": "gzip",
                        "strict-transport-security": "max-age=31536000; includeSubDomains; preload"
                  },
                  "nr_cookies": 1
            },
            {
                  "request_url": "https://telegram.org/file/464001132/3/-1qvqKPZsQQ.17975.png/7d57d7159cf4fbe9b2",
                  "timestamp": "05/06/2022 10:57:54.578465",
                  "request_headers": {
                        "sec-ch-ua": "",
                        "sec-ch-ua-mobile": "?0",
                        "user-agent": "Mozilla/5.0 (Windows NT 10.0; Win64; x64) AppleWebKit/537.36 (KHTML, like Gecko) HeadlessChrome/102.0.5005.63 Safari/537.36",
                        "sec-ch-ua-platform": "",
                        "accept": "image/avif,image/webp,image/apng,image/svg+xml,image/*,*/*;q=0.8",
                        "sec-fetch-site": "same-origin",
                        "sec-fetch-mode": "no-cors",
                        "sec-fetch-dest": "image",
                        "referer": "https://telegram.org/",
                        "accept-encoding": "gzip, deflate, br",
                        "accept-language": "en-GB",
                        "cookie": "stel_ssid=166804baf978665462_18416765889666725392"
                  },
                  "response_headers": {
                        "server": "nginx/1.18.0",
                        "date": "Sun, 05 Jun 2022 08:57:55 GMT",
                        "content-type": "image/png",
                        "content-length": "17998",
                        "cache-control": "max-age=2592000, public",
                        "expires": "Tue, 05 Jul 2022 08:57:55 GMT",
                        "etag": "\"fa9a38332023332be262ffbb44b3d98e6ed68a45\"",
                        "content-encoding": "gzip",
                        "strict-transport-security": "max-age=31536000; includeSubDomains; preload"
                  },
                  "nr_cookies": 1
            },
            {
                  "request_url": "https://telegram.org/file/464001871/3/Uyg3R7LmX1I.17628.png/911807f65dfb4f8f20",
                  "timestamp": "05/06/2022 10:57:54.580466",
                  "request_headers": {
                        "sec-ch-ua": "",
                        "sec-ch-ua-mobile": "?0",
                        "user-agent": "Mozilla/5.0 (Windows NT 10.0; Win64; x64) AppleWebKit/537.36 (KHTML, like Gecko) HeadlessChrome/102.0.5005.63 Safari/537.36",
                        "sec-ch-ua-platform": "",
                        "accept": "image/avif,image/webp,image/apng,image/svg+xml,image/*,*/*;q=0.8",
                        "sec-fetch-site": "same-origin",
                        "sec-fetch-mode": "no-cors",
                        "sec-fetch-dest": "image",
                        "referer": "https://telegram.org/",
                        "accept-encoding": "gzip, deflate, br",
                        "accept-language": "en-GB",
                        "cookie": "stel_ssid=166804baf978665462_18416765889666725392"
                  },
                  "response_headers": {
                        "server": "nginx/1.18.0",
                        "date": "Sun, 05 Jun 2022 08:57:55 GMT",
                        "content-type": "image/png",
                        "content-length": "17622",
                        "cache-control": "max-age=2592000, public",
                        "expires": "Tue, 05 Jul 2022 08:57:55 GMT",
                        "etag": "\"4f4904f57d5c556d26c3f50c2a01b67483833d9d\"",
                        "content-encoding": "gzip",
                        "strict-transport-security": "max-age=31536000; includeSubDomains; preload"
                  },
                  "nr_cookies": 1
            },
            {
                  "request_url": "https://telegram.org/file/464001737/4/Fn57W9l3xI0.15286.png/d4b936ecc2c939f4fa",
                  "timestamp": "05/06/2022 10:57:54.582466",
                  "request_headers": {
                        "sec-ch-ua": "",
                        "sec-ch-ua-mobile": "?0",
                        "user-agent": "Mozilla/5.0 (Windows NT 10.0; Win64; x64) AppleWebKit/537.36 (KHTML, like Gecko) HeadlessChrome/102.0.5005.63 Safari/537.36",
                        "sec-ch-ua-platform": "",
                        "accept": "image/avif,image/webp,image/apng,image/svg+xml,image/*,*/*;q=0.8",
                        "sec-fetch-site": "same-origin",
                        "sec-fetch-mode": "no-cors",
                        "sec-fetch-dest": "image",
                        "referer": "https://telegram.org/",
                        "accept-encoding": "gzip, deflate, br",
                        "accept-language": "en-GB",
                        "cookie": "stel_ssid=166804baf978665462_18416765889666725392"
                  },
                  "response_headers": {
                        "server": "nginx/1.18.0",
                        "date": "Sun, 05 Jun 2022 08:57:55 GMT",
                        "content-type": "image/png",
                        "content-length": "15309",
                        "cache-control": "max-age=2592000, public",
                        "expires": "Tue, 05 Jul 2022 08:57:55 GMT",
                        "etag": "\"93939a07f86b42b04b779841ba81a1ef4ba2d929\"",
                        "content-encoding": "gzip",
                        "strict-transport-security": "max-age=31536000; includeSubDomains; preload"
                  },
                  "nr_cookies": 1
            },
            {
                  "request_url": "https://telegram.org/file/464001560/2/n7EACfx4FPY.16465.png/7318c11715aa2ec45b",
                  "timestamp": "05/06/2022 10:57:54.585530",
                  "request_headers": {
                        "sec-ch-ua": "",
                        "sec-ch-ua-mobile": "?0",
                        "user-agent": "Mozilla/5.0 (Windows NT 10.0; Win64; x64) AppleWebKit/537.36 (KHTML, like Gecko) HeadlessChrome/102.0.5005.63 Safari/537.36",
                        "sec-ch-ua-platform": "",
                        "accept": "image/avif,image/webp,image/apng,image/svg+xml,image/*,*/*;q=0.8",
                        "sec-fetch-site": "same-origin",
                        "sec-fetch-mode": "no-cors",
                        "sec-fetch-dest": "image",
                        "referer": "https://telegram.org/",
                        "accept-encoding": "gzip, deflate, br",
                        "accept-language": "en-GB",
                        "cookie": "stel_ssid=166804baf978665462_18416765889666725392"
                  },
                  "response_headers": {
                        "server": "nginx/1.18.0",
                        "date": "Sun, 05 Jun 2022 08:57:55 GMT",
                        "content-type": "image/png",
                        "content-length": "16488",
                        "cache-control": "max-age=2592000, public",
                        "expires": "Tue, 05 Jul 2022 08:57:55 GMT",
                        "etag": "\"ad24af7a174e71673b28f7e827a85934048a9cd7\"",
                        "content-encoding": "gzip",
                        "strict-transport-security": "max-age=31536000; includeSubDomains; preload"
                  },
                  "nr_cookies": 1
            },
            {
                  "request_url": "https://telegram.org/file/464001402/5/eOMSj3GzJXo.13579.png/f3cec6c451d023c109",
                  "timestamp": "05/06/2022 10:57:54.587530",
                  "request_headers": {
                        "sec-ch-ua": "",
                        "sec-ch-ua-mobile": "?0",
                        "user-agent": "Mozilla/5.0 (Windows NT 10.0; Win64; x64) AppleWebKit/537.36 (KHTML, like Gecko) HeadlessChrome/102.0.5005.63 Safari/537.36",
                        "sec-ch-ua-platform": "",
                        "accept": "image/avif,image/webp,image/apng,image/svg+xml,image/*,*/*;q=0.8",
                        "sec-fetch-site": "same-origin",
                        "sec-fetch-mode": "no-cors",
                        "sec-fetch-dest": "image",
                        "referer": "https://telegram.org/",
                        "accept-encoding": "gzip, deflate, br",
                        "accept-language": "en-GB",
                        "cookie": "stel_ssid=166804baf978665462_18416765889666725392"
                  },
                  "response_headers": {
                        "server": "nginx/1.18.0",
                        "date": "Sun, 05 Jun 2022 08:57:55 GMT",
                        "content-type": "image/png",
                        "content-length": "13592",
                        "cache-control": "max-age=2592000, public",
                        "expires": "Tue, 05 Jul 2022 08:57:55 GMT",
                        "etag": "\"67176c69aa11e9f08d30f489308dc74d85e92ef0\"",
                        "content-encoding": "gzip",
                        "strict-transport-security": "max-age=31536000; includeSubDomains; preload"
                  },
                  "nr_cookies": 1
            },
            {
                  "request_url": "https://telegram.org/file/464001453/3/mNzXWC3RX0c.15740.png/9ce5fa5f3fb74460b4",
                  "timestamp": "05/06/2022 10:57:54.589183",
                  "request_headers": {
                        "sec-ch-ua": "",
                        "sec-ch-ua-mobile": "?0",
                        "user-agent": "Mozilla/5.0 (Windows NT 10.0; Win64; x64) AppleWebKit/537.36 (KHTML, like Gecko) HeadlessChrome/102.0.5005.63 Safari/537.36",
                        "sec-ch-ua-platform": "",
                        "accept": "image/avif,image/webp,image/apng,image/svg+xml,image/*,*/*;q=0.8",
                        "sec-fetch-site": "same-origin",
                        "sec-fetch-mode": "no-cors",
                        "sec-fetch-dest": "image",
                        "referer": "https://telegram.org/",
                        "accept-encoding": "gzip, deflate, br",
                        "accept-language": "en-GB",
                        "cookie": "stel_ssid=166804baf978665462_18416765889666725392"
                  },
                  "response_headers": {
                        "server": "nginx/1.18.0",
                        "date": "Sun, 05 Jun 2022 08:57:55 GMT",
                        "content-type": "image/png",
                        "content-length": "15763",
                        "cache-control": "max-age=2592000, public",
                        "expires": "Tue, 05 Jul 2022 08:57:55 GMT",
                        "etag": "\"9663b372030cf4b80b2b7ab98f8e689847388957\"",
                        "content-encoding": "gzip",
                        "strict-transport-security": "max-age=31536000; includeSubDomains; preload"
                  },
                  "nr_cookies": 1
            },
            {
                  "request_url": "https://telegram.org/file/464001880/3/xOpm7ohoHQ0.12690.png/feb1e161b1d3608613",
                  "timestamp": "05/06/2022 10:57:54.592183",
                  "request_headers": {
                        "sec-ch-ua": "",
                        "sec-ch-ua-mobile": "?0",
                        "user-agent": "Mozilla/5.0 (Windows NT 10.0; Win64; x64) AppleWebKit/537.36 (KHTML, like Gecko) HeadlessChrome/102.0.5005.63 Safari/537.36",
                        "sec-ch-ua-platform": "",
                        "accept": "image/avif,image/webp,image/apng,image/svg+xml,image/*,*/*;q=0.8",
                        "sec-fetch-site": "same-origin",
                        "sec-fetch-mode": "no-cors",
                        "sec-fetch-dest": "image",
                        "referer": "https://telegram.org/",
                        "accept-encoding": "gzip, deflate, br",
                        "accept-language": "en-GB",
                        "cookie": "stel_ssid=166804baf978665462_18416765889666725392"
                  },
                  "response_headers": {
                        "server": "nginx/1.18.0",
                        "date": "Sun, 05 Jun 2022 08:57:55 GMT",
                        "content-type": "image/png",
                        "content-length": "12713",
                        "cache-control": "max-age=2592000, public",
                        "expires": "Tue, 05 Jul 2022 08:57:55 GMT",
                        "etag": "\"9b666309f437dfb32688ee016a9904703de41927\"",
                        "content-encoding": "gzip",
                        "strict-transport-security": "max-age=31536000; includeSubDomains; preload"
                  },
                  "nr_cookies": 1
            },
            {
                  "request_url": "https://telegram.org/img/SiteIconAndroid.svg",
                  "timestamp": "05/06/2022 10:57:54.979586",
                  "request_headers": {
                        "sec-ch-ua": "",
                        "sec-ch-ua-mobile": "?0",
                        "user-agent": "Mozilla/5.0 (Windows NT 10.0; Win64; x64) AppleWebKit/537.36 (KHTML, like Gecko) HeadlessChrome/102.0.5005.63 Safari/537.36",
                        "sec-ch-ua-platform": "",
                        "accept": "image/avif,image/webp,image/apng,image/svg+xml,image/*,*/*;q=0.8",
                        "sec-fetch-site": "same-origin",
                        "sec-fetch-mode": "no-cors",
                        "sec-fetch-dest": "image",
                        "referer": "https://telegram.org/css/telegram.css?230",
                        "accept-encoding": "gzip, deflate, br",
                        "accept-language": "en-GB",
                        "cookie": "stel_ssid=166804baf978665462_18416765889666725392"
                  },
                  "response_headers": {
                        "server": "nginx/1.18.0",
                        "date": "Sun, 05 Jun 2022 08:57:55 GMT",
                        "content-type": "image/svg+xml",
                        "content-length": "999",
                        "last-modified": "Mon, 18 Apr 2022 20:19:52 GMT",
                        "etag": "\"625dc7e8-3e7\"",
                        "expires": "Thu, 09 Jun 2022 08:57:55 GMT",
                        "cache-control": "max-age=345600",
                        "access-control-allow-origin": "*",
                        "accept-ranges": "bytes"
                  },
                  "nr_cookies": 1
            },
            {
                  "request_url": "https://telegram.org/img/twitter.png",
                  "timestamp": "05/06/2022 10:57:54.986587",
                  "request_headers": {
                        "sec-ch-ua": "",
                        "sec-ch-ua-mobile": "?0",
                        "user-agent": "Mozilla/5.0 (Windows NT 10.0; Win64; x64) AppleWebKit/537.36 (KHTML, like Gecko) HeadlessChrome/102.0.5005.63 Safari/537.36",
                        "sec-ch-ua-platform": "",
                        "accept": "image/avif,image/webp,image/apng,image/svg+xml,image/*,*/*;q=0.8",
                        "sec-fetch-site": "same-origin",
                        "sec-fetch-mode": "no-cors",
                        "sec-fetch-dest": "image",
                        "referer": "https://telegram.org/css/telegram.css?230",
                        "accept-encoding": "gzip, deflate, br",
                        "accept-language": "en-GB",
                        "cookie": "stel_ssid=166804baf978665462_18416765889666725392"
                  },
                  "response_headers": {
                        "server": "nginx/1.18.0",
                        "date": "Sun, 05 Jun 2022 08:57:55 GMT",
                        "content-type": "image/png",
                        "content-length": "1272",
                        "last-modified": "Fri, 10 Nov 2017 17:54:14 GMT",
                        "etag": "\"5a05e7c6-4f8\"",
                        "expires": "Thu, 09 Jun 2022 08:57:55 GMT",
                        "cache-control": "max-age=345600",
                        "access-control-allow-origin": "*",
                        "accept-ranges": "bytes"
                  },
                  "nr_cookies": 1
            },
            {
                  "request_url": "https://telegram.org/img/SiteiOS.jpg?2",
                  "timestamp": "05/06/2022 10:57:54.992588",
                  "request_headers": {
                        "sec-ch-ua": "",
                        "sec-ch-ua-mobile": "?0",
                        "user-agent": "Mozilla/5.0 (Windows NT 10.0; Win64; x64) AppleWebKit/537.36 (KHTML, like Gecko) HeadlessChrome/102.0.5005.63 Safari/537.36",
                        "sec-ch-ua-platform": "",
                        "accept": "image/avif,image/webp,image/apng,image/svg+xml,image/*,*/*;q=0.8",
                        "sec-fetch-site": "same-origin",
                        "sec-fetch-mode": "no-cors",
                        "sec-fetch-dest": "image",
                        "referer": "https://telegram.org/css/telegram.css?230",
                        "accept-encoding": "gzip, deflate, br",
                        "accept-language": "en-GB",
                        "cookie": "stel_ssid=166804baf978665462_18416765889666725392"
                  },
                  "response_headers": {
                        "server": "nginx/1.18.0",
                        "date": "Sun, 05 Jun 2022 08:57:55 GMT",
                        "content-type": "image/jpeg",
                        "content-length": "31305",
                        "last-modified": "Sat, 09 May 2020 18:58:54 GMT",
                        "etag": "\"5eb6fd6e-7a49\"",
                        "expires": "Thu, 09 Jun 2022 08:57:55 GMT",
                        "cache-control": "max-age=345600",
                        "access-control-allow-origin": "*",
                        "accept-ranges": "bytes"
                  },
                  "nr_cookies": 1
            },
            {
                  "request_url": "https://telegram.org/js/tgsticker-worker.js?12",
                  "timestamp": "05/06/2022 10:57:54.999661",
                  "request_headers": {
                        "sec-ch-ua": "",
                        "sec-ch-ua-mobile": "?0",
                        "user-agent": "Mozilla/5.0 (Windows NT 10.0; Win64; x64) AppleWebKit/537.36 (KHTML, like Gecko) HeadlessChrome/102.0.5005.63 Safari/537.36",
                        "sec-ch-ua-platform": "",
                        "accept": "*/*",
                        "sec-fetch-site": "same-origin",
                        "sec-fetch-mode": "same-origin",
                        "sec-fetch-dest": "worker",
                        "referer": "https://telegram.org/",
                        "accept-encoding": "gzip, deflate, br",
                        "accept-language": "en-GB",
                        "cookie": "stel_ssid=166804baf978665462_18416765889666725392"
                  },
                  "response_headers": {
                        "server": "nginx/1.18.0",
                        "date": "Sun, 05 Jun 2022 08:57:55 GMT",
                        "content-type": "application/javascript",
                        "last-modified": "Fri, 18 Dec 2020 15:22:10 GMT",
                        "etag": "W/\"5fdcc922-16d0\"",
                        "expires": "Thu, 09 Jun 2022 08:57:55 GMT",
                        "cache-control": "max-age=345600",
                        "strict-transport-security": "max-age=31536000; includeSubDomains; preload",
                        "content-encoding": "gzip"
                  },
                  "nr_cookies": 1
            },
            {
                  "request_url": "https://telegram.org/img/SiteDesktop.jpg?2",
                  "timestamp": "05/06/2022 10:57:55.002661",
                  "request_headers": {
                        "sec-ch-ua": "",
                        "sec-ch-ua-mobile": "?0",
                        "user-agent": "Mozilla/5.0 (Windows NT 10.0; Win64; x64) AppleWebKit/537.36 (KHTML, like Gecko) HeadlessChrome/102.0.5005.63 Safari/537.36",
                        "sec-ch-ua-platform": "",
                        "accept": "image/avif,image/webp,image/apng,image/svg+xml,image/*,*/*;q=0.8",
                        "sec-fetch-site": "same-origin",
                        "sec-fetch-mode": "no-cors",
                        "sec-fetch-dest": "image",
                        "referer": "https://telegram.org/css/telegram.css?230",
                        "accept-encoding": "gzip, deflate, br",
                        "accept-language": "en-GB",
                        "cookie": "stel_ssid=166804baf978665462_18416765889666725392"
                  },
                  "response_headers": {
                        "server": "nginx/1.18.0",
                        "date": "Sun, 05 Jun 2022 08:57:55 GMT",
                        "content-type": "image/jpeg",
                        "content-length": "97628",
                        "last-modified": "Tue, 11 Jun 2019 13:49:53 GMT",
                        "etag": "\"5cffb181-17d5c\"",
                        "expires": "Thu, 09 Jun 2022 08:57:55 GMT",
                        "cache-control": "max-age=345600",
                        "access-control-allow-origin": "*",
                        "accept-ranges": "bytes"
                  },
                  "nr_cookies": 1
            },
            {
                  "request_url": "https://telegram.org/img/SiteIconApple.svg",
                  "timestamp": "05/06/2022 10:57:55.008662",
                  "request_headers": {
                        "sec-ch-ua": "",
                        "sec-ch-ua-mobile": "?0",
                        "user-agent": "Mozilla/5.0 (Windows NT 10.0; Win64; x64) AppleWebKit/537.36 (KHTML, like Gecko) HeadlessChrome/102.0.5005.63 Safari/537.36",
                        "sec-ch-ua-platform": "",
                        "accept": "image/avif,image/webp,image/apng,image/svg+xml,image/*,*/*;q=0.8",
                        "sec-fetch-site": "same-origin",
                        "sec-fetch-mode": "no-cors",
                        "sec-fetch-dest": "image",
                        "referer": "https://telegram.org/css/telegram.css?230",
                        "accept-encoding": "gzip, deflate, br",
                        "accept-language": "en-GB",
                        "cookie": "stel_ssid=166804baf978665462_18416765889666725392"
                  },
                  "response_headers": {
                        "server": "nginx/1.18.0",
                        "date": "Sun, 05 Jun 2022 08:57:55 GMT",
                        "content-type": "image/svg+xml",
                        "content-length": "443",
                        "last-modified": "Mon, 18 Apr 2022 20:19:52 GMT",
                        "etag": "\"625dc7e8-1bb\"",
                        "expires": "Thu, 09 Jun 2022 08:57:55 GMT",
                        "cache-control": "max-age=345600",
                        "access-control-allow-origin": "*",
                        "accept-ranges": "bytes"
                  },
                  "nr_cookies": 1
            },
            {
                  "request_url": "https://telegram.org/img/SiteAndroid.jpg?2",
                  "timestamp": "05/06/2022 10:57:55.014732",
                  "request_headers": {
                        "sec-ch-ua": "",
                        "sec-ch-ua-mobile": "?0",
                        "user-agent": "Mozilla/5.0 (Windows NT 10.0; Win64; x64) AppleWebKit/537.36 (KHTML, like Gecko) HeadlessChrome/102.0.5005.63 Safari/537.36",
                        "sec-ch-ua-platform": "",
                        "accept": "image/avif,image/webp,image/apng,image/svg+xml,image/*,*/*;q=0.8",
                        "sec-fetch-site": "same-origin",
                        "sec-fetch-mode": "no-cors",
                        "sec-fetch-dest": "image",
                        "referer": "https://telegram.org/css/telegram.css?230",
                        "accept-encoding": "gzip, deflate, br",
                        "accept-language": "en-GB",
                        "cookie": "stel_ssid=166804baf978665462_18416765889666725392"
                  },
                  "response_headers": {
                        "server": "nginx/1.18.0",
                        "date": "Sun, 05 Jun 2022 08:57:55 GMT",
                        "content-type": "image/jpeg",
                        "content-length": "21090",
                        "last-modified": "Sat, 09 May 2020 18:58:54 GMT",
                        "etag": "\"5eb6fd6e-5262\"",
                        "expires": "Thu, 09 Jun 2022 08:57:55 GMT",
                        "cache-control": "max-age=345600",
                        "access-control-allow-origin": "*",
                        "accept-ranges": "bytes"
                  },
                  "nr_cookies": 1
            },
            {
                  "request_url": "https://telegram.org/js/rlottie-wasm.js",
                  "timestamp": "05/06/2022 10:57:55.326346",
                  "request_headers": {
                        "user-agent": "Mozilla/5.0 (Windows NT 10.0; Win64; x64) AppleWebKit/537.36 (KHTML, like Gecko) HeadlessChrome/102.0.5005.63 Safari/537.36",
                        "accept": "*/*",
                        "sec-fetch-site": "same-origin",
                        "sec-fetch-mode": "no-cors",
                        "sec-fetch-dest": "script",
                        "referer": "https://telegram.org/js/tgsticker-worker.js?12",
                        "accept-encoding": "gzip, deflate, br",
                        "accept-language": "en-GB",
                        "cookie": "stel_ssid=166804baf978665462_18416765889666725392"
                  },
                  "response_headers": {
                        "server": "nginx/1.18.0",
                        "date": "Sun, 05 Jun 2022 08:57:55 GMT",
                        "content-type": "application/javascript",
                        "last-modified": "Tue, 14 Jul 2020 22:03:36 GMT",
                        "etag": "W/\"5f0e2bb8-188f9\"",
                        "expires": "Thu, 09 Jun 2022 08:57:55 GMT",
                        "cache-control": "max-age=345600",
                        "strict-transport-security": "max-age=31536000; includeSubDomains; preload",
                        "content-encoding": "gzip"
                  },
                  "nr_cookies": 1
            },
            {
                  "request_url": "https://telegram.org/img/t_logo_sprite.svg",
                  "timestamp": "05/06/2022 10:57:55.444882",
                  "request_headers": {
                        "sec-ch-ua": "",
                        "sec-ch-ua-mobile": "?0",
                        "user-agent": "Mozilla/5.0 (Windows NT 10.0; Win64; x64) AppleWebKit/537.36 (KHTML, like Gecko) HeadlessChrome/102.0.5005.63 Safari/537.36",
                        "sec-ch-ua-platform": "",
                        "accept": "image/avif,image/webp,image/apng,image/svg+xml,image/*,*/*;q=0.8",
                        "sec-fetch-site": "same-origin",
                        "sec-fetch-mode": "no-cors",
                        "sec-fetch-dest": "image",
                        "referer": "https://telegram.org/",
                        "accept-encoding": "gzip, deflate, br",
                        "accept-language": "en-GB",
                        "cookie": "stel_ssid=166804baf978665462_18416765889666725392"
                  },
                  "response_headers": {
                        "server": "nginx/1.18.0",
                        "date": "Sun, 05 Jun 2022 08:57:56 GMT",
                        "content-type": "image/svg+xml",
                        "content-length": "23116",
                        "last-modified": "Tue, 19 Apr 2022 11:15:29 GMT",
                        "etag": "\"625e99d1-5a4c\"",
                        "expires": "Thu, 09 Jun 2022 08:57:56 GMT",
                        "cache-control": "max-age=345600",
                        "access-control-allow-origin": "*",
                        "accept-ranges": "bytes"
                  },
                  "nr_cookies": 1
            },
            {
                  "request_url": "https://telegram.org/img/t_main_Android_demo.mp4",
                  "timestamp": "05/06/2022 10:57:55.451884",
                  "request_headers": {
                        "sec-ch-ua": "",
                        "accept-encoding": "identity;q=1, *;q=0",
                        "sec-ch-ua-mobile": "?0",
                        "user-agent": "Mozilla/5.0 (Windows NT 10.0; Win64; x64) AppleWebKit/537.36 (KHTML, like Gecko) HeadlessChrome/102.0.5005.63 Safari/537.36",
                        "sec-ch-ua-platform": "",
                        "accept": "*/*",
                        "sec-fetch-site": "same-origin",
                        "sec-fetch-mode": "no-cors",
                        "sec-fetch-dest": "video",
                        "referer": "https://telegram.org/",
                        "accept-language": "en-GB",
                        "range": "bytes=0-",
                        "cookie": "stel_ssid=166804baf978665462_18416765889666725392"
                  },
                  "response_headers": {
                        "server": "nginx/1.18.0",
                        "date": "Sun, 05 Jun 2022 08:57:56 GMT",
                        "content-type": "video/mp4",
                        "content-length": "250838",
                        "last-modified": "Sat, 09 May 2020 18:58:54 GMT",
                        "etag": "\"5eb6fd6e-3d3d6\"",
                        "expires": "Thu, 09 Jun 2022 08:57:56 GMT",
                        "cache-control": "max-age=345600",
                        "access-control-allow-origin": "*",
                        "content-range": "bytes 0-250837/250838"
                  },
                  "nr_cookies": 1
            },
            {
                  "request_url": "https://telegram.org/img/t_main_iOS_demo.mp4",
                  "timestamp": "05/06/2022 10:57:55.479113",
                  "request_headers": {
                        "sec-ch-ua": "",
                        "accept-encoding": "identity;q=1, *;q=0",
                        "sec-ch-ua-mobile": "?0",
                        "user-agent": "Mozilla/5.0 (Windows NT 10.0; Win64; x64) AppleWebKit/537.36 (KHTML, like Gecko) HeadlessChrome/102.0.5005.63 Safari/537.36",
                        "sec-ch-ua-platform": "",
                        "accept": "*/*",
                        "sec-fetch-site": "same-origin",
                        "sec-fetch-mode": "no-cors",
                        "sec-fetch-dest": "video",
                        "referer": "https://telegram.org/",
                        "accept-language": "en-GB",
                        "range": "bytes=0-",
                        "cookie": "stel_ssid=166804baf978665462_18416765889666725392"
                  },
                  "response_headers": {
                        "server": "nginx/1.18.0",
                        "date": "Sun, 05 Jun 2022 08:57:56 GMT",
                        "content-type": "video/mp4",
                        "content-length": "244748",
                        "last-modified": "Sat, 09 May 2020 18:58:54 GMT",
                        "etag": "\"5eb6fd6e-3bc0c\"",
                        "expires": "Thu, 09 Jun 2022 08:57:56 GMT",
                        "cache-control": "max-age=345600",
                        "access-control-allow-origin": "*",
                        "content-range": "bytes 0-244747/244748"
                  },
                  "nr_cookies": 1
            },
            {
                  "request_url": "https://telegram.org/js/rlottie-wasm.wasm",
                  "timestamp": "05/06/2022 10:57:55.597572",
                  "request_headers": {
                        "user-agent": "Mozilla/5.0 (Windows NT 10.0; Win64; x64) AppleWebKit/537.36 (KHTML, like Gecko) HeadlessChrome/102.0.5005.63 Safari/537.36",
                        "accept": "*/*",
                        "sec-fetch-site": "same-origin",
                        "sec-fetch-mode": "cors",
                        "sec-fetch-dest": "empty",
                        "referer": "https://telegram.org/js/tgsticker-worker.js?12",
                        "accept-encoding": "gzip, deflate, br",
                        "accept-language": "en-GB",
                        "cookie": "stel_ssid=166804baf978665462_18416765889666725392"
                  },
                  "response_headers": {
                        "server": "nginx/1.18.0",
                        "date": "Sun, 05 Jun 2022 08:57:56 GMT",
                        "content-type": "application/wasm",
                        "last-modified": "Tue, 14 Jul 2020 22:03:36 GMT",
                        "etag": "W/\"5f0e2bb8-5f508\"",
                        "expires": "Thu, 09 Jun 2022 08:57:56 GMT",
                        "cache-control": "max-age=345600",
                        "strict-transport-security": "max-age=31536000; includeSubDomains; preload",
                        "content-encoding": "gzip"
                  },
                  "nr_cookies": 1
            },
            {
                  "request_url": "https://telegram.org/js/pako-inflate.min.js",
                  "timestamp": "05/06/2022 10:57:55.597572",
                  "request_headers": {
                        "user-agent": "Mozilla/5.0 (Windows NT 10.0; Win64; x64) AppleWebKit/537.36 (KHTML, like Gecko) HeadlessChrome/102.0.5005.63 Safari/537.36",
                        "accept": "*/*",
                        "sec-fetch-site": "same-origin",
                        "sec-fetch-mode": "no-cors",
                        "sec-fetch-dest": "script",
                        "referer": "https://telegram.org/js/tgsticker-worker.js?12",
                        "accept-encoding": "gzip, deflate, br",
                        "accept-language": "en-GB",
                        "cookie": "stel_ssid=166804baf978665462_18416765889666725392"
                  },
                  "response_headers": {
                        "server": "nginx/1.18.0",
                        "date": "Sun, 05 Jun 2022 08:57:56 GMT",
                        "content-type": "application/javascript",
                        "last-modified": "Fri, 04 Oct 2019 11:37:17 GMT",
                        "etag": "W/\"5d972eed-589a\"",
                        "expires": "Thu, 09 Jun 2022 08:57:56 GMT",
                        "cache-control": "max-age=345600",
                        "strict-transport-security": "max-age=31536000; includeSubDomains; preload",
                        "content-encoding": "gzip"
                  },
                  "nr_cookies": 1
            },
            {
                  "request_url": "https://telegram.org/img/t_main_Android_demo.mp4",
                  "timestamp": "05/06/2022 10:57:56.059298",
                  "request_headers": {
                        "sec-ch-ua": "",
                        "accept-encoding": "identity;q=1, *;q=0",
                        "sec-ch-ua-mobile": "?0",
                        "user-agent": "Mozilla/5.0 (Windows NT 10.0; Win64; x64) AppleWebKit/537.36 (KHTML, like Gecko) HeadlessChrome/102.0.5005.63 Safari/537.36",
                        "sec-ch-ua-platform": "",
                        "accept": "*/*",
                        "sec-fetch-site": "same-origin",
                        "sec-fetch-mode": "no-cors",
                        "sec-fetch-dest": "video",
                        "referer": "https://telegram.org/",
                        "accept-language": "en-GB",
                        "range": "bytes=229376-",
                        "cookie": "stel_ssid=166804baf978665462_18416765889666725392"
                  },
                  "response_headers": {
                        "server": "nginx/1.18.0",
                        "date": "Sun, 05 Jun 2022 08:57:56 GMT",
                        "content-type": "video/mp4",
                        "content-length": "21462",
                        "last-modified": "Sat, 09 May 2020 18:58:54 GMT",
                        "etag": "\"5eb6fd6e-3d3d6\"",
                        "expires": "Thu, 09 Jun 2022 08:57:56 GMT",
                        "cache-control": "max-age=345600",
                        "access-control-allow-origin": "*",
                        "content-range": "bytes 229376-250837/250838"
                  },
                  "nr_cookies": 1
            },
            {
                  "request_url": "https://telegram.org/img/t_main_iOS_demo.mp4",
                  "timestamp": "05/06/2022 10:57:56.074312",
                  "request_headers": {
                        "sec-ch-ua": "",
                        "accept-encoding": "identity;q=1, *;q=0",
                        "sec-ch-ua-mobile": "?0",
                        "user-agent": "Mozilla/5.0 (Windows NT 10.0; Win64; x64) AppleWebKit/537.36 (KHTML, like Gecko) HeadlessChrome/102.0.5005.63 Safari/537.36",
                        "sec-ch-ua-platform": "",
                        "accept": "*/*",
                        "sec-fetch-site": "same-origin",
                        "sec-fetch-mode": "no-cors",
                        "sec-fetch-dest": "video",
                        "referer": "https://telegram.org/",
                        "accept-language": "en-GB",
                        "range": "bytes=229376-",
                        "cookie": "stel_ssid=166804baf978665462_18416765889666725392"
                  },
                  "response_headers": {
                        "server": "nginx/1.18.0",
                        "date": "Sun, 05 Jun 2022 08:57:56 GMT",
                        "content-type": "video/mp4",
                        "content-length": "15372",
                        "last-modified": "Sat, 09 May 2020 18:58:54 GMT",
                        "etag": "\"5eb6fd6e-3bc0c\"",
                        "expires": "Thu, 09 Jun 2022 08:57:56 GMT",
                        "cache-control": "max-age=345600",
                        "access-control-allow-origin": "*",
                        "content-range": "bytes 229376-244747/244748"
                  },
                  "nr_cookies": 1
            },
            {
                  "request_url": "https://telegram.org/js/tgsticker-worker.js?12",
                  "timestamp": "05/06/2022 10:57:56.106702",
                  "request_headers": {
                        "sec-ch-ua": "",
                        "sec-ch-ua-mobile": "?0",
                        "user-agent": "Mozilla/5.0 (Windows NT 10.0; Win64; x64) AppleWebKit/537.36 (KHTML, like Gecko) HeadlessChrome/102.0.5005.63 Safari/537.36",
                        "sec-ch-ua-platform": "",
                        "accept": "*/*",
                        "sec-fetch-site": "same-origin",
                        "sec-fetch-mode": "same-origin",
                        "sec-fetch-dest": "worker",
                        "referer": "https://telegram.org/",
                        "accept-encoding": "gzip, deflate, br",
                        "accept-language": "en-GB",
                        "cookie": "stel_ssid=166804baf978665462_18416765889666725392"
                  },
                  "response_headers": null,
                  "nr_cookies": 1
            }
      ]
}